migrations/0001_bootstrap.py
migrations/0002_rollover_shards.py
migrations/0003_allfields_key.py
migrations/0004_rollover_shards.py
migrations/0005_rollover_shards.py
migrations/0006_rollover_shards.py
migrations/0008_cleanup_leftover_rollover_metadata.py
migrations/0009_upgrade_relations_and_texts_to_v2.py
migrations/0010_fix_corrupt_indexes.py
migrations/0011_materialize_labelset_ids.py
migrations/0012_rollover_shards.py
migrations/0013_rollover_shards.py
migrations/0014_rollover_shards.py
migrations/0015_targeted_rollover.py
migrations/0016_upgrade_to_paragraphs_v2.py
migrations/0017_multiple_writable_shards.py
migrations/0018_purge_orphan_kbslugs.py
migrations/0019_upgrade_to_paragraphs_v3.py
migrations/0020_drain_nodes_from_cluster.py
migrations/0021_overwrite_vectorsets_key.py
migrations/0022_fix_paragraph_deletion_bug.py
migrations/0023_backfill_pg_catalog.py
migrations/0025_assign_models_to_kbs_v2.py
migrations/0026_fix_high_cardinality_content_types.py
migrations/0027_rollover_texts3.py
migrations/0028_extracted_vectors_reference.py
migrations/0029_backfill_field_status.py
migrations/0030_label_deduplication.py
migrations/0031_languages_deduplication.py
migrations/0032_remove_old_relations.py
migrations/0033_rollover_nidx_relation_2.py
migrations/0034_rollover_nidx_texts_3.py
migrations/0035_rollover_nidx_texts_4.py
migrations/0036_backfill_catalog_slug.py
migrations/0037_backfill_catalog_facets.py
migrations/0038_backfill_catalog_field_labels.py
migrations/0039_backfill_converation_splits_metadata.py
migrations/0040_migrate_search_configurations.py
migrations/0041_reindex_conversations.py
migrations/__init__.py
migrations/pg/0001_bootstrap.py
migrations/pg/0002_catalog.py
migrations/pg/0003_catalog_kbid_index.py
migrations/pg/0004_catalog_facets.py
migrations/pg/0005_purge_tasks_index.py
migrations/pg/0006_catalog_title_indexes.py
migrations/pg/0007_catalog_slug.py
migrations/pg/0008_catalog_facets.py
migrations/pg/0009_extract_facets_safety.py
nucliadb-6.11.1.post5854.dist-info/METADATA
nucliadb-6.11.1.post5854.dist-info/WHEEL
nucliadb-6.11.1.post5854.dist-info/entry_points.txt
nucliadb-6.11.1.post5854.dist-info/top_level.txt
nucliadb-6.11.1.post5854.dist-info/RECORD
